zxpath2/Element.py
zxpath2/Element_List.py
zxpath2/Text_Element.py
zxpath2/__init__.py
zxpath2/base_library.py
zxpath2-1.1.3.dist-info/LICENSE
zxpath2-1.1.3.dist-info/METADATA
zxpath2-1.1.3.dist-info/WHEEL
zxpath2-1.1.3.dist-info/top_level.txt
zxpath2-1.1.3.dist-info/RECORD
