Metadata-Version: 2.1
Name: zxpath2
Version: 1.1.3
Summary: 操作更方便的xpath
Home-page: https://pypi.org/project/zxpath2/
Author: zlyuan
Author-email: 1277260932@qq.com
License: GNU GENERAL PUBLIC LICENSE
Platform: all
Classifier: Environment :: Web Environment
Classifier: Intended Audience :: Developers
Classifier: Operating System :: OS Independent
Classifier: Programming Language :: Python :: 3
Requires-Dist: lxml
